jyotichart/__init__.py
jyotichart-4.2.2.dist-info/LICENSE
jyotichart-4.2.2.dist-info/METADATA
jyotichart-4.2.2.dist-info/WHEEL
jyotichart-4.2.2.dist-info/top_level.txt
jyotichart-4.2.2.dist-info/RECORD
