Metadata-Version: 2.2
Name: jyotichart
Version: 4.2.2
Summary: This package takes the Ascendant sign and planet details as input and generates astrological charts in North Indian and South Indian format.
Author-email: Shyam Bhat <bhatshyam.modernastrologer@gmail.com>
Project-URL: Homepage, https://github.com/VicharaVandana/jyotichart
Project-URL: Bug Tracker, https://github.com/VicharaVandana/jyotichart/issues
Classifier: Programming Language :: Python :: 3
Classifier: License :: OSI Approved :: MIT License
Classifier: Operating System :: OS Independent
Requires-Python: >=3.7
License-File: LICENSE
